Authors.rst
MANIFEST.in
NEWS
README.md
setup.cfg
setup.py
bap/.DS_Store
bap/__init__.py
bap/__init__.pyc
bap/bap1ProjectClass.py
bap/bap2ProjectClass.py
bap/bapFragProjectClass.py
bap/bapHelp.py
bap/cli.pyc
bap/cli_bap2.py
bap/cli_bap_bulk_frag.py
bap/cli_bap_frag.py
bap/cli_old_dontEdit.py
bap/cli_reanno.py
bap/__pycache__/.DS_Store
bap/__pycache__/__init__.cpython-36.pyc
bap/__pycache__/__init__.cpython-38.pyc
bap/__pycache__/annoall.cpython-36.pyc
bap/__pycache__/bap1ProjectClass.cpython-36.pyc
bap/__pycache__/bap2ProjectClass.cpython-36.pyc
bap/__pycache__/bapFragProjectClass.cpython-36.pyc
bap/__pycache__/bapHelp.cpython-36.pyc
bap/__pycache__/bapHelp.cpython-38.pyc
bap/__pycache__/bapProjectClass.cpython-36.pyc
bap/__pycache__/cli.cpython-36.pyc
bap/__pycache__/cli_bap2.cpython-36.pyc
bap/__pycache__/cli_bap_bulk_frag.cpython-36.pyc
bap/__pycache__/cli_bap_frag.cpython-36.pyc
bap/__pycache__/cli_old_dontEdit.cpython-36.pyc
bap/__pycache__/cli_reanno.cpython-36.pyc
bap/anno/.DS_Store
bap/anno/TSS/.DS_Store
bap/anno/TSS/GRCh37.refGene.TSS.bed
bap/anno/TSS/GRCh38.refGene.TSS.bed
bap/anno/TSS/GRCm37.refGene.TSS.bed
bap/anno/TSS/GRCm38.refGene.TSS.bed
bap/anno/TSS/hg19-mm10.refGene.TSS.bed
bap/anno/TSS/hg19-mm10_nochr.refGene.TSS.bed
bap/anno/TSS/hg19.refGene.TSS.bed
bap/anno/TSS/hg19_mm10_c.refGene.TSS.bed
bap/anno/TSS/hg38.refGene.TSS.bed
bap/anno/TSS/mm10.refGene.TSS.bed
bap/anno/TSS/mm9.refGene.TSS.bed
bap/anno/bedtools/chrom_GRCh37.sizes
bap/anno/bedtools/chrom_GRCh38.sizes
bap/anno/bedtools/chrom_GRCm37.sizes
bap/anno/bedtools/chrom_GRCm38.sizes
bap/anno/bedtools/chrom_hg19-mm10.sizes
bap/anno/bedtools/chrom_hg19-mm10_nochr.sizes
bap/anno/bedtools/chrom_hg19.sizes
bap/anno/bedtools/chrom_hg19_mm10_c.sizes
bap/anno/bedtools/chrom_hg38.sizes
bap/anno/bedtools/chrom_mm10.sizes
bap/anno/bedtools/chrom_mm9.sizes
bap/anno/blacklist/GRCh37.full.blacklist.bed
bap/anno/blacklist/GRCh38.full.blacklist.bed
bap/anno/blacklist/GRCm37.full.blacklist.bed
bap_atac.egg-info/PKG-INFO
bap_atac.egg-info/SOURCES.txt
bap_atac.egg-info/dependency_links.txt
bap_atac.egg-info/entry_points.txt
bap_atac.egg-info/not-zip-safe
bap_atac.egg-info/requires.txt
bap_atac.egg-info/top_level.txt