Metadata-Version: 1.1
Name: bap-atac
Version: 0.7.0
Summary: Bead-based scATAC-seq data Processing.
Home-page: https://github.com/caleblareau/bap
Author: Caleb Lareau
Author-email: clareau@gmail.com
License: MIT
Platform: any
Classifier: Development Status :: 5 - Production/Stable
Classifier: Environment :: Console
Classifier: Intended Audience :: Developers
Classifier: License :: OSI Approved :: MIT License
Classifier: Operating System :: POSIX
Classifier: Operating System :: MacOS
Classifier: Operating System :: Unix
Classifier: Programming Language :: Python
Classifier: Programming Language :: Python :: 3
Classifier: Topic :: Software Development :: Libraries :: Python Modules
